torchrunx/__init__.py
torchrunx/__main__.py
torchrunx/agent.py
torchrunx/integrations/__init__.py
torchrunx/integrations/cli.py
torchrunx/integrations/lightning.py
torchrunx/launcher.py
torchrunx/py.typed
torchrunx/utils/__init__.py
torchrunx/utils/comm.py
torchrunx/utils/environment.py
torchrunx/utils/errors.py
torchrunx/utils/log_handling.py
torchrunx/utils/log_streaming.py
torchrunx/worker.py
torchrunx-0.3.4.dist-info/WHEEL
torchrunx-0.3.4.dist-info/METADATA
torchrunx-0.3.4.dist-info/RECORD
